pyprowl/__init__.py
pyprowl/test.py
pyprowl-3.0.1.dist-info/LICENSE
pyprowl-3.0.1.dist-info/METADATA
pyprowl-3.0.1.dist-info/WHEEL
pyprowl-3.0.1.dist-info/top_level.txt
pyprowl-3.0.1.dist-info/RECORD
