Metadata-Version: 2.1
Name: pyprowl
Version: 3.0.1
Summary: Prowl API wrapper for Python
Home-page: https://github.com/toddrob99/pyprowl
Author: Todd Roberts
Author-email: todd@toddrob.com
License: UNKNOWN
Platform: UNKNOWN
Classifier: Programming Language :: Python :: 2.7
Classifier: Programming Language :: Python :: 3
Classifier: License :: OSI Approved :: GNU General Public License v3 (GPLv3)
Classifier: Operating System :: OS Independent
